mini_apollo/__init__.py
mini_apollo/client.py
mini_apollo/config.py
mini_apollo-0.1.2.dist-info/licenses/LICENSE
mini_apollo-0.1.2.dist-info/METADATA
mini_apollo-0.1.2.dist-info/WHEEL
mini_apollo-0.1.2.dist-info/top_level.txt
mini_apollo-0.1.2.dist-info/RECORD
