Metadata-Version: 2.4
Name: mini-apollo
Version: 0.1.2
Summary: A lightweight Python SDK for Apollo Config.
License-Expression: MIT
Requires-Python: >=3.9
License-File: LICENSE
Requires-Dist: aiohttp>=3.12.0
Requires-Dist: requests>=2.30.0
Provides-Extra: test
Requires-Dist: pytest>=6.0.0; extra == "test"
Requires-Dist: pytest-asyncio>=0.21.0; extra == "test"
Requires-Dist: pytest-mock>=3.10.0; extra == "test"
Requires-Dist: responses>=0.23.0; extra == "test"
Requires-Dist: aioresponses>=0.7.0; extra == "test"
Dynamic: license-file
